inscd/__init__.py
inscd/_base.py
inscd/_listener.py
inscd/_ruler.py
inscd/_unifier.py
inscd/datahub/__init__.py
inscd/datahub/assist17.py
inscd/datahub/datahub.py
inscd/datahub/frcsub.py
inscd/datahub/junyi734.py
inscd/datahub/math1.py
inscd/datahub/math2.py
inscd/datahub/matmat.py
inscd/datahub/neurips20.py
inscd/datahub/utils.py
inscd/extractor/__init__.py
inscd/extractor/cdmfkc.py
inscd/extractor/default.py
inscd/extractor/lightgcn.py
inscd/extractor/orcdf.py
inscd/extractor/rcd.py
inscd/extractor/scd.py
inscd/interfunc/__init__.py
inscd/interfunc/_util.py
inscd/interfunc/cdmfkc.py
inscd/interfunc/dp.py
inscd/interfunc/irt.py
inscd/interfunc/kancd.py
inscd/interfunc/kscd.py
inscd/interfunc/mf.py
inscd/interfunc/mirt.py
inscd/interfunc/ncd.py
inscd/interfunc/rcd.py
inscd/interfunc/scd.py
inscd/models/__init__.py
inscd/models/classical/__init__.py
inscd/models/classical/mirt.py
inscd/models/graph/__init__.py
inscd/models/graph/orcdf.py
inscd/models/graph/rcd.py
inscd/models/graph/scd.py
inscd/models/neural/__init__.py
inscd/models/neural/cdmfkc.py
inscd/models/neural/kancd.py
inscd/models/neural/kscd.py
inscd/models/neural/ncdm.py
inscd-1.1.0.dist-info/LICENSE
inscd-1.1.0.dist-info/METADATA
inscd-1.1.0.dist-info/WHEEL
inscd-1.1.0.dist-info/top_level.txt
inscd-1.1.0.dist-info/RECORD
