Metadata-Version: 2.1
Name: inscd
Version: 1.1.0
Author: Junhao Shen
Author-email: shenjh@stu.ecnu.edu.cn
License: MIT license
License-File: LICENSE
Requires-Dist: torch
Requires-Dist: tqdm
Requires-Dist: numpy >=1.16.5
Requires-Dist: scikit-learn
Requires-Dist: pandas
Requires-Dist: dgl
